{
  "main": {
    "id": "f2de169e0c30ea64",
    "type": "split",
    "children": [
      {
        "id": "3abf6c6484d152c8",
        "type": "tabs",
        "children": [
          {
            "id": "f3b376147910efd7",
            "type": "leaf",
            "state": {
              "type": "markdown",
              "state": {
                "file": "Anomaly Detection/How would you design a Real-time Anomaly Detection Algorithm?.md",
                "mode": "preview",
                "backlinks": true,
                "source": false
              }
            }
          },
          {
            "id": "503914c1c04e138f",
            "type": "leaf",
            "state": {
              "type": "empty",
              "state": {}
            }
          }
        ]
      }
    ],
    "direction": "vertical"
  },
  "left": {
    "id": "50454f8a814d2ef3",
    "type": "split",
    "children": [
      {
        "id": "d8c2682098593a0f",
        "type": "tabs",
        "children": [
          {
            "id": "68653de1a4f0344c",
            "type": "leaf",
            "state": {
              "type": "file-explorer",
              "state": {
                "sortOrder": "alphabetical"
              }
            }
          },
          {
            "id": "814bfdd88b6aa17c",
            "type": "leaf",
            "state": {
              "type": "search",
              "state": {
                "query": "",
                "matchingCase": false,
                "explainSearch": false,
                "collapseAll": false,
                "extraContext": false,
                "sortOrder": "alphabetical"
              }
            }
          },
          {
            "id": "e70bb691019d21cb",
            "type": "leaf",
            "state": {
              "type": "bookmarks",
              "state": {}
            }
          },
          {
            "id": "a0aba55b04e80d1c",
            "type": "leaf",
            "state": {
              "type": "mk-file-view",
              "state": {}
            }
          }
        ]
      }
    ],
    "direction": "horizontal",
    "width": 383.5
  },
  "right": {
    "id": "2d28c0b415c679ab",
    "type": "split",
    "children": [
      {
        "id": "da6f8d70ae68fb78",
        "type": "tabs",
        "children": [
          {
            "id": "b7d8abbad29522e5",
            "type": "leaf",
            "state": {
              "type": "backlink",
              "state": {
                "file": "Anomaly Detection/How would you design a Real-time Anomaly Detection Algorithm?.md",
                "collapseAll": false,
                "extraContext": false,
                "sortOrder": "alphabetical",
                "showSearch": false,
                "searchQuery": "",
                "backlinkCollapsed": false,
                "unlinkedCollapsed": true
              }
            }
          },
          {
            "id": "3f2f521592a21b50",
            "type": "leaf",
            "state": {
              "type": "outgoing-link",
              "state": {
                "file": "Anomaly Detection/How would you design a Real-time Anomaly Detection Algorithm?.md",
                "linksCollapsed": false,
                "unlinkedCollapsed": true
              }
            }
          },
          {
            "id": "98fd45e91dcb96fe",
            "type": "leaf",
            "state": {
              "type": "tag",
              "state": {
                "sortOrder": "frequency",
                "useHierarchy": true
              }
            }
          },
          {
            "id": "b2645714ce8ff74a",
            "type": "leaf",
            "state": {
              "type": "outline",
              "state": {
                "file": "Anomaly Detection/How would you design a Real-time Anomaly Detection Algorithm?.md"
              }
            }
          },
          {
            "id": "66443909f0fabcfa",
            "type": "leaf",
            "state": {
              "type": "reminder-list",
              "state": {}
            }
          },
          {
            "id": "6021e8b627cad934",
            "type": "leaf",
            "state": {
              "type": "Strange New Worlds",
              "state": {}
            }
          },
          {
            "id": "654b4deca80fe076",
            "type": "leaf",
            "state": {
              "type": "copilot-chat-view",
              "state": {}
            }
          }
        ],
        "currentTab": 3
      }
    ],
    "direction": "horizontal",
    "width": 300,
    "collapsed": true
  },
  "left-ribbon": {
    "hiddenItems": {
      "switcher:Open quick switcher": false,
      "graph:Open graph view": false,
      "canvas:Create new canvas": false,
      "daily-notes:Open today's daily note": false,
      "templates:Insert template": false,
      "command-palette:Open command palette": false,
      "markdown-importer:Open format converter": false,
      "omnisearch:Omnisearch": false,
      "publish:Publish changes...": false
    }
  },
  "active": "f3b376147910efd7",
  "lastOpenFiles": [
    "Anomaly Detection/How is Mahalanobis Distance used in Outlier Detection?.md",
    "Anomaly Detection/How is Anomaly Detection performed in Models of Time-Varying Processes?.md",
    "Anomaly Detection/How does Dictionary Learning perform Anomaly Detection?.md",
    "Anomaly Detection/Explain what is Anomaly Detection?.md",
    "Anomaly Detection/Explain the difference between Outlier Detection vs Novelty Detection.md",
    "Index_of_idk-knowledge-graph.md",
    "Unsupervised Learning/Are GANs unsupervised?.md",
    "Scikit-Learn/_Index_of_Scikit-Learn.md",
    "Statistics/Statistics.md",
    "readme.md",
    "Untitled.canvas",
    "Unsupervised Learning/Index_of_Unsupervised Learning.md",
    "Unsupervised Learning/What are some applications of Unsupervised Learning?.md",
    "Unsupervised Learning/What are some common Machine Learning problems that Unsupervised Learning can help with?.md",
    "Unsupervised Learning/What are some differences between Unsupervised Learning and Reinforcement Learning?.md",
    "Unsupervised Learning/What’s the LDA algorithm? Give an example..md",
    "SVM/How to use one-class SVM for Anomalies Detections?.md",
    "SVM/How to select Kernel for SVM?.md",
    "SVM/How does the value of Gamma affect the SVM?.md",
    "SVM/How does the value of C affect the SVM?.md",
    "SVM/How do you approximate RBF kernel to scale with large numbers of training samples?.md",
    "SVM/For N dimensional data set what is the minimum possible number of Support Vectors?.md",
    "SVM/Explain the dual form of SVM formulation.md",
    "SVM/Does Redundant data affect an SVM-based classifier?.md",
    "SVM/Does linear SVMs suffer from the Curse of Dimensionality?.md",
    "PCA/Can you explain PAC learning theory intuitively?.md",
    "SVM/Can Support Vector Machines be used for Outlier Detection?.md",
    "Attachements/Screenshot 2023-12-09 at 2.18.43 AM.png",
    "Attachements/Screenshot 2023-12-09 at 2.18.18 AM.png",
    "Attachements/Screenshot 2023-12-09 at 2.18.00 AM.png",
    "Attachements/Screenshot 2023-12-09 at 2.17.41 AM.png",
    "Attachements/Screenshot 2023-12-09 at 2.17.18 AM.png",
    "Attachements/Screenshot 2023-12-09 at 2.16.58 AM.png",
    "Attachements/Screenshot 2023-12-09 at 2.16.35 AM.png",
    "Attachements/Screenshot 2023-12-09 at 2.16.26 AM.png",
    "Attachements/Screenshot 2023-12-09 at 2.15.52 AM.png",
    "Attachements/Screenshot 2023-12-09 at 2.15.26 AM.png",
    "Spaces/Home",
    "Spaces",
    "image-zoom.css",
    "Untitled 1.canvas",
    "8.6 PCA",
    "8.5 Model Evaluation",
    "8.4 Dimensionality Reduction",
    "8.3 Data Processing",
    "8.2 Bias & Variance",
    "8.1 Curse of Dimensionality",
    "8.0 Feature Engineering"
  ]
}